pysifen/__init__.py
pysifen/sign.py
pysifen-0.1.0.dist-info/METADATA
pysifen-0.1.0.dist-info/WHEEL
pysifen-0.1.0.dist-info/RECORD
