Metadata-Version: 2.1
Name: pysifen
Version: 0.1.0
Summary: 
Author: josecuev
Author-email: jmcuev89@gmail.com
Requires-Python: >=3.11,<4.0
Classifier: Programming Language :: Python :: 3
Classifier: Programming Language :: Python :: 3.11
Requires-Dist: fastapi (>=0.101.0,<0.102.0)
